{"d":{"__metadata":{"id":"https://smartmesh.sharepoint.com/_api/Web/Lists(guid'1ce6b9be-37d6-453f-b455-338607215d5c')","uri":"https://smartmesh.sharepoint.com/_api/Web/Lists(guid'1ce6b9be-37d6-453f-b455-338607215d5c')","etag":"\"0\"","type":"SP.List"},"FirstUniqueAncestorSecurableObject":{"__deferred":{"uri":"https://smartmesh.sharepoint.com/_api/Web/Lists(guid'1ce6b9be-37d6-453f-b455-338607215d5c')/FirstUniqueAncestorSecurableObject"}},"RoleAssignments":{"__deferred":{"uri":"https://smartmesh.sharepoint.com/_api/Web/Lists(guid'1ce6b9be-37d6-453f-b455-338607215d5c')/RoleAssignments"}},"ContentTypes":{"__deferred":{"uri":"https://smartmesh.sharepoint.com/_api/Web/Lists(guid'1ce6b9be-37d6-453f-b455-338607215d5c')/ContentTypes"}},"CreatablesInfo":{"__deferred":{"uri":"https://smartmesh.sharepoint.com/_api/Web/Lists(guid'1ce6b9be-37d6-453f-b455-338607215d5c')/CreatablesInfo"}},"DefaultView":{"__deferred":{"uri":"https://smartmesh.sharepoint.com/_api/Web/Lists(guid'1ce6b9be-37d6-453f-b455-338607215d5c')/DefaultView"}},"DescriptionResource":{"__deferred":{"uri":"https://smartmesh.sharepoint.com/_api/Web/Lists(guid'1ce6b9be-37d6-453f-b455-338607215d5c')/DescriptionResource"}},"EventReceivers":{"__deferred":{"uri":"https://smartmesh.sharepoint.com/_api/Web/Lists(guid'1ce6b9be-37d6-453f-b455-338607215d5c')/EventReceivers"}},"Fields":{"__deferred":{"uri":"https://smartmesh.sharepoint.com/_api/Web/Lists(guid'1ce6b9be-37d6-453f-b455-338607215d5c')/Fields"}},"Forms":{"__deferred":{"uri":"https://smartmesh.sharepoint.com/_api/Web/Lists(guid'1ce6b9be-37d6-453f-b455-338607215d5c')/Forms"}},"InformationRightsManagementSettings":{"__deferred":{"uri":"https://smartmesh.sharepoint.com/_api/Web/Lists(guid'1ce6b9be-37d6-453f-b455-338607215d5c')/InformationRightsManagementSettings"}},"Items":{"__deferred":{"uri":"https://smartmesh.sharepoint.com/_api/Web/Lists(guid'1ce6b9be-37d6-453f-b455-338607215d5c')/Items"}},"ParentWeb":{"__deferred":{"uri":"https://smartmesh.sharepoint.com/_api/Web/Lists(guid'1ce6b9be-37d6-453f-b455-338607215d5c')/ParentWeb"}},"RootFolder":{"__deferred":{"uri":"https://smartmesh.sharepoint.com/_api/Web/Lists(guid'1ce6b9be-37d6-453f-b455-338607215d5c')/RootFolder"}},"TitleResource":{"__deferred":{"uri":"https://smartmesh.sharepoint.com/_api/Web/Lists(guid'1ce6b9be-37d6-453f-b455-338607215d5c')/TitleResource"}},"UserCustomActions":{"__deferred":{"uri":"https://smartmesh.sharepoint.com/_api/Web/Lists(guid'1ce6b9be-37d6-453f-b455-338607215d5c')/UserCustomActions"}},"Views":{"__deferred":{"uri":"https://smartmesh.sharepoint.com/_api/Web/Lists(guid'1ce6b9be-37d6-453f-b455-338607215d5c')/Views"}},"WorkflowAssociations":{"__deferred":{"uri":"https://smartmesh.sharepoint.com/_api/Web/Lists(guid'1ce6b9be-37d6-453f-b455-338607215d5c')/WorkflowAssociations"}},"AllowContentTypes":true,"BaseTemplate":125,"BaseType":0,"ContentTypesEnabled":false,"CrawlNonDefaultViews":false,"Created":"2014-03-10T13:16:25Z","DefaultContentApprovalWorkflowId":"00000000-0000-0000-0000-000000000000","Description":"","Direction":"none","DocumentTemplateUrl":null,"DraftVersionVisibility":0,"EnableAttachments":true,"EnableFolderCreation":true,"EnableMinorVersions":false,"EnableModeration":false,"EnableVersioning":false,"EntityTypeName":"OData__x005f_catalogs_x002f_appdata","ForceCheckout":false,"HasExternalDataSource":false,"Hidden":true,"Id":"1ce6b9be-37d6-453f-b455-338607215d5c","ImageUrl":"/_layouts/15/images/itgen.png?rev=33","IrmEnabled":false,"IrmExpire":false,"IrmReject":false,"IsApplicationList":false,"IsCatalog":false,"IsPrivate":false,"ItemCount":0,"LastItemDeletedDate":"2014-03-10T13:16:25Z","LastItemModifiedDate":"2014-03-10T13:16:25Z","ListItemEntityTypeFullName":"SP.Data.OData__x005f_catalogs_x002f_appdataItem","MultipleDataList":false,"NoCrawl":true,"ParentWebUrl":"/","ParserDisabled":false,"ServerTemplateCanCreateFolders":true,"TemplateFeatureId":"00000000-0000-0000-0000-000000000000","Title":"appdata"}}